README.txt
prettydate.ini
setup.py
prettydate/__init__.py
prettydate/pretty_date.py
prettydate/web.py
prettydate.egg-info/PKG-INFO
prettydate.egg-info/SOURCES.txt
prettydate.egg-info/dependency_links.txt
prettydate.egg-info/entry_points.txt
prettydate.egg-info/not-zip-safe
prettydate.egg-info/requires.txt
prettydate.egg-info/top_level.txt