Metadata-Version: 1.0
Name: prettydate
Version: 0.2
Summary: pretty formatting of dates
Home-page: https://svn.openplans.org/svn/standalone/prettyDate
Author: The Open Planning Project
Author-email: jhammel@openplans.org
License: GPL
Platform: UNKNOWN
